superbox_utils/__init__.py
superbox_utils/version.py
superbox_utils/argparse/__init__.py
superbox_utils/argparse/argparse.py
superbox_utils/asyncio/__init__.py
superbox_utils/asyncio/asyncio.py
superbox_utils/config/__init__.py
superbox_utils/config/exception.py
superbox_utils/config/loader.py
superbox_utils/core/exception.py
superbox_utils/dict/__init__.py
superbox_utils/dict/data_dict.py
superbox_utils/hass/__init__.py
superbox_utils/hass/config.py
superbox_utils/logging/__init__.py
superbox_utils/logging/config.py
superbox_utils/logging/handler.py
superbox_utils/logging/log.py
superbox_utils/mqtt/__init__.py
superbox_utils/mqtt/config.py
superbox_utils/mqtt/connect.py
superbox_utils/text/__init__.py
superbox_utils/text/text.py
superbox_utils/yaml/__init__.py
superbox_utils/yaml/dumper.py
superbox_utils/yaml/loader.py
superbox_utils-2023.6.dist-info/LICENSE
superbox_utils-2023.6.dist-info/METADATA
superbox_utils-2023.6.dist-info/WHEEL
superbox_utils-2023.6.dist-info/top_level.txt
superbox_utils-2023.6.dist-info/RECORD
