Metadata-Version: 2.1
Name: superbox-utils
Version: 2023.6
Summary: Utilities for Superbox Python Packages.
Home-page: https://github.com/superbox-dev/superbox-utils
Author: Michael Hacker
Author-email: mh@superbox.one
License: Apache-2.0 license
Project-URL: Source Code, https://github.com/superbox-dev/superbox-utils
Project-URL: Bug Reports, https://github.com/superbox-dev/superbox-utils/issues
Classifier: Development Status :: 5 - Production/Stable
Classifier: License :: OSI Approved :: Apache Software License
Classifier: Programming Language :: Python :: 3
Classifier: Programming Language :: Python :: 3.8
Classifier: Programming Language :: Python :: 3.9
Classifier: Programming Language :: Python :: 3.10
Classifier: Programming Language :: Python :: 3.11
Classifier: Programming Language :: Python :: 3 :: Only
Classifier: Operating System :: POSIX :: Linux
Classifier: Topic :: Utilities
Requires-Python: >=3.8
License-File: LICENSE
Requires-Dist: pyyaml (~=6.0)
Provides-Extra: mqtt
Requires-Dist: asyncio-mqtt (==0.16.1) ; extra == 'mqtt'
Requires-Dist: paho-mqtt (==1.6.1) ; extra == 'mqtt'
